openkitx403/__init__.py
openkitx403/core.py
openkitx403/middleware.py
openkitx403-0.1.5.dist-info/METADATA
openkitx403-0.1.5.dist-info/WHEEL
openkitx403-0.1.5.dist-info/RECORD
